jogos_python/__init__.py
jogos_python/caixa.png
jogos_python/fazenda.png
jogos_python/galinha.png
jogos_python/ovo.png
jogos_python/pintinho.png
jogos_python-0.11.1.dist-info/METADATA
jogos_python-0.11.1.dist-info/WHEEL
jogos_python-0.11.1.dist-info/top_level.txt
jogos_python-0.11.1.dist-info/RECORD
