Metadata-Version: 2.1
Name: jogos-python
Version: 0.11.1
Summary: Facilita a criação de jogos com Python
Home-page: https://jogos-python.readthedocs.io
Author: LIpE/UFRJ
Author-email: lipe@poli.ufrj.br
License: UNKNOWN
Platform: UNKNOWN
Requires-Dist: pygame
